char_draw/__init__.py
char_draw/canvas.py
char_draw/display_list.py
char_draw/graph.py
dashboard/__init__.py
dashboard/dashboard.py
dashboard/version.py
dashboard_cli/__init__.py
dashboard_cli/config.py
dashboard_cli/server.py
data_sources/__init__.py
data_sources/csv_data.py
data_sources/data_table.py
data_sources/elastic_data.py
data_sources/json_data.py
data_sources/logs_data.py
data_sources/odbc_data.py
data_sources/proc_data.py
data_sources/remote_data.py
data_sources/syslog_data.py
terminal_dashboard-0.0.6.data/scripts/dashboard
terminal_dashboard-0.0.6.dist-info/LICENSE
terminal_dashboard-0.0.6.dist-info/METADATA
terminal_dashboard-0.0.6.dist-info/WHEEL
terminal_dashboard-0.0.6.dist-info/top_level.txt
terminal_dashboard-0.0.6.dist-info/RECORD
