Metadata-Version: 2.1
Name: terminal-dashboard
Version: 0.0.6
Summary: A tool for showing a customizable graphical dashboard of various data sources in a terminal
Home-page: http://github.com/jpfxgood/dashboard
Author: James Goodwin
Author-email: dashboard@jlgoodwin.com
License: MIT
Keywords: dashboard,monitor,terminal,graphs
Platform: UNKNOWN
Classifier: Programming Language :: Python :: 3
Classifier: License :: OSI Approved :: MIT License
Classifier: Operating System :: OS Independent
Requires-Python: >=3.6
Requires-Dist: psutil
Requires-Dist: elasticsearch
Requires-Dist: paramiko
Requires-Dist: keyring
Requires-Dist: pyodbc
Requires-Dist: python-dateutil
